pyhtime.py
pyhtime-0.0.1.dist-info/DESCRIPTION.rst
pyhtime-0.0.1.dist-info/METADATA
pyhtime-0.0.1.dist-info/RECORD
pyhtime-0.0.1.dist-info/WHEEL
pyhtime-0.0.1.dist-info/metadata.json
pyhtime-0.0.1.dist-info/top_level.txt
