Metadata-Version: 2.0
Name: pyhtime
Version: 0.0.1
Summary: 一个用来将 datetime 时间转化成更加人性化的`时间描述字符串`
Home-page: https://github.com/chenjiandongx/pytiemago
Author: chenjiandongx
Author-email: chenjiandongx@qq.com
License: MIT
Platform: UNKNOWN
Requires-Dist: moment
